connection_pool/__init__.py
connection_pool-0.0.2.dist-info/METADATA
connection_pool-0.0.2.dist-info/RECORD
connection_pool-0.0.2.dist-info/WHEEL
connection_pool-0.0.2.dist-info/top_level.txt
