Metadata-Version: 2.1
Name: connection-pool
Version: 0.0.2
Summary: thread safe connection pool
Home-page: https://github.com/zhouyl/ConnectionPool
Author: zhouyl
Author-email: 81438567@qq.com
License: MIT
Platform: UNKNOWN
Classifier: Operating System :: OS Independent
Classifier: Intended Audience :: Developers
Classifier: License :: OSI Approved :: MIT License
Classifier: Programming Language :: Python
Classifier: Programming Language :: Python :: Implementation
Classifier: Programming Language :: Python :: 2
Classifier: Programming Language :: Python :: 2.7
Classifier: Programming Language :: Python :: 3
Classifier: Programming Language :: Python :: 3.4
Classifier: Programming Language :: Python :: 3.5
Classifier: Programming Language :: Python :: 3.6
Classifier: Topic :: Software Development :: Libraries :: Python Modules
